dejima/__init__.py
dejima/__main__.py
dejima/api.py
dejima/cli.py
dejima/constants.py
dejima/db.py
dejima/exceptions.py
dejima/plugin.py
dejima/.mypy_cache/.gitignore
dejima/.mypy_cache/CACHEDIR.TAG
dejima/.mypy_cache/missing_stubs
dejima/.mypy_cache/3.9/@plugins_snapshot.json
dejima/.mypy_cache/3.9/__future__.data.json
dejima/.mypy_cache/3.9/__future__.meta.json
dejima/.mypy_cache/3.9/_ast.data.json
dejima/.mypy_cache/3.9/_ast.meta.json
dejima/.mypy_cache/3.9/_collections_abc.data.json
dejima/.mypy_cache/3.9/_collections_abc.meta.json
dejima/.mypy_cache/3.9/_thread.data.json
dejima/.mypy_cache/3.9/_thread.meta.json
dejima/.mypy_cache/3.9/abc.data.json
dejima/.mypy_cache/3.9/abc.meta.json
dejima/.mypy_cache/3.9/argparse.data.json
dejima/.mypy_cache/3.9/argparse.meta.json
dejima/.mypy_cache/3.9/array.data.json
dejima/.mypy_cache/3.9/array.meta.json
dejima/.mypy_cache/3.9/ast.data.json
dejima/.mypy_cache/3.9/ast.meta.json
dejima/.mypy_cache/3.9/builtins.data.json
dejima/.mypy_cache/3.9/builtins.meta.json
dejima/.mypy_cache/3.9/codecs.data.json
dejima/.mypy_cache/3.9/codecs.meta.json
dejima/.mypy_cache/3.9/dataclasses.data.json
dejima/.mypy_cache/3.9/dataclasses.meta.json
dejima/.mypy_cache/3.9/genericpath.data.json
dejima/.mypy_cache/3.9/genericpath.meta.json
dejima/.mypy_cache/3.9/io.data.json
dejima/.mypy_cache/3.9/io.meta.json
dejima/.mypy_cache/3.9/mmap.data.json
dejima/.mypy_cache/3.9/mmap.meta.json
dejima/.mypy_cache/3.9/posix.data.json
dejima/.mypy_cache/3.9/posix.meta.json
dejima/.mypy_cache/3.9/posixpath.data.json
dejima/.mypy_cache/3.9/posixpath.meta.json
dejima/.mypy_cache/3.9/string.data.json
dejima/.mypy_cache/3.9/string.meta.json
dejima/.mypy_cache/3.9/subprocess.data.json
dejima/.mypy_cache/3.9/subprocess.meta.json
dejima/.mypy_cache/3.9/sys.data.json
dejima/.mypy_cache/3.9/sys.meta.json
dejima/.mypy_cache/3.9/threading.data.json
dejima/.mypy_cache/3.9/threading.meta.json
dejima/.mypy_cache/3.9/time.data.json
dejima/.mypy_cache/3.9/time.meta.json
dejima-2.1.1.dist-info/LICENSE
dejima-2.1.1.dist-info/METADATA
dejima-2.1.1.dist-info/WHEEL
dejima-2.1.1.dist-info/entry_points.txt
dejima-2.1.1.dist-info/top_level.txt
dejima-2.1.1.dist-info/RECORD
